ptranslator/__init__.py
ptranslator/ptranslator.py
ptranslator-1.5.3.dist-info/LICENSE
ptranslator-1.5.3.dist-info/METADATA
ptranslator-1.5.3.dist-info/WHEEL
ptranslator-1.5.3.dist-info/entry_points.txt
ptranslator-1.5.3.dist-info/top_level.txt
ptranslator-1.5.3.dist-info/RECORD
