Metadata-Version: 2.1
Name: ptranslator
Version: 1.5.3
Summary: Simple yet effective module for translating that uses Google Translate
Home-page: https://github.com/Raptr3x/python-translator
Author: Bogdan Caleta Ivkovic
Author-email: bogdan.caleta@gmail.com
License: UNKNOWN
Platform: UNKNOWN
Classifier: Programming Language :: Python :: 3
Classifier: License :: OSI Approved :: MIT License
Classifier: Operating System :: OS Independent
